<?xml version="1.0" encoding="UTF-8"?>
<simulation xmlns:xsi="http://www.w3.org/2001/XMLSchema-instance">
  <params>
    <delta_t>0.01</delta_t>
    <end_time>1.0</end_time>
    <epsilon>0.5</epsilon>
    <sigma>1.0</sigma>
    <output>sim</output>
    <frequency>20</frequency>
  </params>
  <clusters>
    <cuboid>
      <pos>
        <x>0</x>
        <y>0</y>
        <z>0</z>
      </pos>
      <vel>
        <x>0</x>
        <y>0</y>
        <z>0</z>
      </vel>
      <dim>
        <x>40</x>
        <y>8</y>
        <z>1</z>
      </dim>
      <mass>1.0</mass>
      <spacing>1.125</spacing>
      <brownVel>0.1</brownVel>
      <brownDim>2</brownDim>
    </cuboid> 
    <sphere>
        <center>
        <x>15</x>
        <y>15</y>
        <z>0</z>
      </center>
      <radius>10</radius>
      <mass>1.0</mass>
      <spacing>1.125</spacing>
    </sphere>
    <cuboid>
      <pos>
        <x>15</x>
        <y>15</y>
        <z>0</z>
      </pos>
      <vel>
        <x>0</x>
        <y>-10</y>
        <z>0</z>
      </vel>
      <dim>
        <x>8</x>
        <y>8</y>
        <z>1</z>
      </dim>
      <mass>1.0</mass>
      <spacing>1.125</spacing>
      <brownVel>0.1</brownVel>
      <brownDim>2</brownDim>
    </cuboid>
  </clusters>
</simulation>
